<instance version="6" description="" template="ebps">
	<list name="extensions">
		<template_reference name="exts" value="ebpextensions\entity_blueprint_ext" List.ItemID="1544196321" List.ParentItemID="1544196321">
			<instance_reference name="animator_attachments" value="attachments\attachment_lists\civilizations\rus\buildings\defense_wooden_fort_rus\defense_wooden_fort_rus" overrideParent="True" />
			<bool name="browsable_in_editor" value="True" overrideParent="True" />
		</template_reference>
		<template_reference name="exts" value="ebpextensions\cost_ext" overrideParent="True" List.ItemID="-1618369463" List.ParentItemID="-1618369463">
			<group name="time_cost">
				<enum_table name="cost">
					<float name="action" value="0" />
					<float name="popcap" value="0" />
					<float name="command" value="0" />
					<float name="food" value="0" />
					<float name="wood" value="175" overrideParent="True" />
					<float name="stone" value="0" />
					<float name="gold" value="0" />
					<float name="militia_hre" value="0" />
					<float name="merc_byz" value="0" />
				</enum_table>
				<float name="time_seconds" value="60" overrideParent="True" />
				<int name="time_turns" value="0" />
			</group>
		</template_reference>
		<template_reference name="exts" value="ebpextensions\health_ext" List.ItemID="2017155034" List.ParentItemID="2017155034">
			<float name="hitpoints" value="2625" overrideParent="True" />
		</template_reference>
		<template_reference name="exts" value="ebpextensions\sight_ext" List.ItemID="462979593" List.ParentItemID="462979593">
			<group name="sight_package">
				<float name="inner_radius" value="35" overrideParent="True" />
			</group>
		</template_reference>
		<template_reference name="exts" value="ebpextensions\type_ext" List.ItemID="-33111220" List.ParentItemID="-33111220">
			<list name="unit_type_list" overrideParent="True">
				<enum name="unit_type" value="military" List.ItemID="-93015753" />
				<enum name="unit_type" value="building" List.ItemID="-895519570" />
				<enum name="unit_type" value="tower" List.ItemID="-460573169" />
				<enum name="unit_type" value="outpost" List.ItemID="-806901411" />
				<enum name="unit_type" value="defensive_structure" List.ItemID="-1918045140" />
				<enum name="unit_type" value="siegeable" List.ItemID="-1420983528" />
				<enum name="unit_type" value="town_bell_target" List.ItemID="727937933" />
				<enum name="unit_type" value="scar_outpost" overrideParent="True" List.ItemID="1523253941" />
				<enum name="unit_type" value="has_default_building_weapons" List.ItemID="992109768" />
				<enum name="unit_type" value="wooden_fortress" List.ItemID="-812933312" />
			</list>
			<list name="race_type_list" overrideParent="True">
				<instance_reference name="race_type" value="racebps\rus" List.ItemID="669766667" />
			</list>
		</template_reference>
		<template_reference name="exts" value="ebpextensions\ui_ext" List.ItemID="-1221151512" List.ParentItemID="-1221151512">
			<file name="icon_name" value="races\rus\buildings\wooden_fortress" overrideParent="True" />
			<bool name="is_unique_to_race" value="True" overrideParent="True" />
			<group name="ui_codex_info">
				<bool name="exclusive" value="True" overrideParent="True" />
			</group>
			<list name="ui_extra_infos" overrideParent="True">
				<template_reference name="ui_extra_info" value="info\ui_extra_info" List.ItemID="-323085724">
					<file name="icon" value="influence_buff" overrideParent="True" />
					<locstring name="description" value="11191462" />
					<template_reference name="description_formatter" value="">
					</template_reference>
				</template_reference>
			</list>
			<string name="telemetry_name" value="Wooden Fortress" overrideParent="True" />
		</template_reference>
		<template_reference name="exts" value="ebpextensions\upgrade_ext" List.ItemID="536671903" List.ParentItemID="536671903">
			<list name="standard_upgrades" overrideParent="True">
				<instance_reference name="upgrade" value="upgrade\races\rus\research\upgrade_wooden_castle_arrowslits_rus" overrideParent="True" List.ItemID="505292280" />
				<instance_reference name="upgrade" value="upgrade\races\rus\research\upgrade_wooden_castle_turret_rus" List.ItemID="744222795" />
				<instance_reference name="upgrade" value="upgrade\races\rus\research\upgrade_wooden_castle_watch_rus" List.ItemID="1619570598" />
				<instance_reference name="upgrade" value="upgrade\races\rus\research\upgrade_wooden_castle_springald_rus" List.ItemID="-489709763" />
			</list>
		</template_reference>
		<template_reference name="exts" value="ebpextensions\site_ext" List.ItemID="389041388" List.ParentItemID="389041388">
			<bool name="snap_to_construction_grid" value="True" overrideParent="True" />
		</template_reference>
		<template_reference name="exts" value="ebpextensions\construction_ext" List.ItemID="1700796307" List.ParentItemID="1700796307">
			<template_reference name="construction_health_option" value="options\ebpextensions\constructionext\construction_health_option">
				<float name="initial_health" value="200" overrideParent="True" />
			</template_reference>
			<group name="on_construction_complete_state_tree_refs">
				<string name="while_construction_complete_entity_state_tree_ref" value="building_construction_complete\buildings\outpost_construction_complete" overrideParent="True" />
			</group>
			<bool name="construction_site_erase_inactive" value="False" overrideParent="True" />
		</template_reference>
		<template_reference name="exts" value="ebpextensions\spawner_ext" List.ItemID="32036034" List.ParentItemID="32036034">
			<instance_reference name="rally_pass_type" value="pass_types\infantry" overrideParent="True" />
		</template_reference>
		<template_reference name="exts" value="ebpextensions\burn_ext" List.ItemID="-1218905965" List.ParentItemID="-1218905965">
			<float name="on_fire_damage_per_sec" value="12" overrideParent="True" />
		</template_reference>
		<template_reference name="exts" value="ebpextensions\combat_ext" List.ItemID="2086910227" List.ParentItemID="2086910227">
			<list name="hardpoints" overrideParent="True">
				<group name="hardpoint" comment="Arrowslits Slot" List.ItemID="791129112">
					<float name="parent_hardpoint" value="-1" />
					<list name="weapon_table">
						<group name="weapon" List.ItemID="-1350557460">
							<group name="heading">
								<float name="x" value="0" />
								<float name="y" value="0.3" />
								<float name="z" value="1" />
							</group>
							<float name="length" value="0" />
							<group name="origin">
								<float name="x" value="0" />
								<float name="y" value="6" />
								<float name="z" value="0" />
							</group>
							<enum name="type" value="default" />
							<template_reference name="weapon_entity_attachment" value="options\attachment_types\entity_create_attachment">
								<template_reference name="entity_attach_data" value="attachments\attach_data_entity">
									<template_reference name="attach_data" value="attachments\attach_data">
										<string name="marker_name_parent" value="" />
										<string name="parent_rigidbody_target_name" value="" />
										<enum name="game_object_attachment_type" value="scenegraph" />
									</template_reference>
									<instance_reference name="ebp" value="ebps\races\core\weapons\wpn_siege_outpost_arrows" />
									<group name="attachment_flags">
										<bool name="sim_only" value="False" />
										<bool name="no_pathfinding" value="False" />
										<bool name="not_snappable" value="False" />
										<bool name="restore_snap_to_ground_on_detach" value="False" />
										<bool name="no_sim_update" value="True" />
										<bool name="join_parent_squad" value="False" />
										<bool name="redirect_damage_to_parent_entity" value="True" />
										<bool name="assign_as_attachment_combat_leader" value="False" />
										<bool name="assign_as_attachment_movement_leader" value="False" />
										<bool name="receive_parent_animations" value="False" />
										<bool name="receive_parent_death" value="False" />
									</group>
								</template_reference>
								<list name="possible_blueprint_updates">
								</list>
							</template_reference>
							<template_reference name="non_entity_weapon_wrapper" value="">
							</template_reference>
						</group>
					</list>
					<bool name="receives_attack_commands" value="True" />
					<string name="base_marker" value="" />
					<list name="preferred_inventory_item_categories">
					</list>
					<list name="firing_offset_markers">
						<string name="marker" value="fx_muz_arrow_00" List.ItemID="-860853702" />
						<string name="marker" value="fx_muz_arrow_01" List.ItemID="-1021474275" />
						<string name="marker" value="fx_muz_arrow_02" List.ItemID="469763009" />
						<string name="marker" value="fx_muz_arrow_03" List.ItemID="229209306" />
					</list>
					<bool name="initialize_weapons_on_creation" value="False" />
					<string name="offhand_marker" value="" />
				</group>
				<group name="hardpoint" comment="Springald Slot" List.ItemID="1892411336">
					<float name="parent_hardpoint" value="-1" />
					<list name="weapon_table">
						<group name="weapon" List.ItemID="-1719943956">
							<group name="heading">
								<float name="x" value="0" />
								<float name="y" value="0" />
								<float name="z" value="1" />
							</group>
							<float name="length" value="0" />
							<group name="origin">
								<float name="x" value="0" />
								<float name="y" value="0.5" />
								<float name="z" value="0" />
							</group>
							<enum name="type" value="default" />
							<template_reference name="weapon_entity_attachment" value="options\attachment_types\entity_create_attachment">
								<template_reference name="entity_attach_data" value="attachments\attach_data_entity">
									<template_reference name="attach_data" value="attachments\attach_data">
										<string name="marker_name_parent" value="" />
										<string name="parent_rigidbody_target_name" value="" />
										<enum name="game_object_attachment_type" value="scenegraph" />
									</template_reference>
									<instance_reference name="ebp" value="ebps\races\rus\weapons\wpn_range_wooden_fort_springald_a_rus" overrideParent="True" />
									<group name="attachment_flags">
										<bool name="sim_only" value="False" />
										<bool name="no_pathfinding" value="False" />
										<bool name="not_snappable" value="False" />
										<bool name="restore_snap_to_ground_on_detach" value="False" />
										<bool name="no_sim_update" value="False" />
										<bool name="join_parent_squad" value="False" />
										<bool name="redirect_damage_to_parent_entity" value="True" />
										<bool name="assign_as_attachment_combat_leader" value="False" />
										<bool name="assign_as_attachment_movement_leader" value="False" />
										<bool name="receive_parent_animations" value="False" />
										<bool name="receive_parent_death" value="False" />
									</group>
								</template_reference>
								<list name="possible_blueprint_updates">
								</list>
							</template_reference>
							<template_reference name="non_entity_weapon_wrapper" value="">
							</template_reference>
						</group>
					</list>
					<bool name="receives_attack_commands" value="True" overrideParent="True" />
					<string name="base_marker" value="" />
					<list name="preferred_inventory_item_categories">
					</list>
					<list name="firing_offset_markers">
					</list>
					<bool name="initialize_weapons_on_creation" value="False" overrideParent="True" />
					<string name="offhand_marker" value="" />
				</group>
				<group name="hardpoint" comment="Springald Slot - District Bonus" List.ItemID="1017668990">
					<float name="parent_hardpoint" value="-1" />
					<list name="weapon_table">
						<group name="weapon" List.ItemID="574822382">
							<group name="heading">
								<float name="x" value="0" />
								<float name="y" value="0" />
								<float name="z" value="1" />
							</group>
							<float name="length" value="0" />
							<group name="origin">
								<float name="x" value="0" />
								<float name="y" value="0.5" />
								<float name="z" value="0" />
							</group>
							<enum name="type" value="default" />
							<template_reference name="weapon_entity_attachment" value="options\attachment_types\entity_create_attachment">
								<template_reference name="entity_attach_data" value="attachments\attach_data_entity">
									<template_reference name="attach_data" value="attachments\attach_data">
										<string name="marker_name_parent" value="" />
										<string name="parent_rigidbody_target_name" value="" />
										<enum name="game_object_attachment_type" value="scenegraph" />
									</template_reference>
									<instance_reference name="ebp" value="ebps\races\rus\weapons\wpn_range_wooden_fort_springald_b_rus" overrideParent="True" />
									<group name="attachment_flags">
										<bool name="sim_only" value="False" />
										<bool name="no_pathfinding" value="False" />
										<bool name="not_snappable" value="False" />
										<bool name="restore_snap_to_ground_on_detach" value="False" />
										<bool name="no_sim_update" value="False" />
										<bool name="join_parent_squad" value="False" />
										<bool name="redirect_damage_to_parent_entity" value="True" />
										<bool name="assign_as_attachment_combat_leader" value="False" />
										<bool name="assign_as_attachment_movement_leader" value="False" />
										<bool name="receive_parent_animations" value="False" />
										<bool name="receive_parent_death" value="False" />
									</group>
								</template_reference>
								<list name="possible_blueprint_updates">
								</list>
							</template_reference>
							<template_reference name="non_entity_weapon_wrapper" value="">
							</template_reference>
						</group>
					</list>
					<bool name="receives_attack_commands" value="True" overrideParent="True" />
					<string name="base_marker" value="" />
					<list name="preferred_inventory_item_categories">
					</list>
					<list name="firing_offset_markers">
					</list>
					<bool name="initialize_weapons_on_creation" value="False" overrideParent="True" />
					<string name="offhand_marker" value="" />
				</group>
				<group name="hardpoint" comment="Murderholes Slot" List.ItemID="-1201071698">
					<float name="parent_hardpoint" value="-1" />
					<list name="weapon_table">
						<group name="weapon" List.ItemID="-827783118">
							<group name="heading">
								<float name="x" value="0" />
								<float name="y" value="0" />
								<float name="z" value="1" />
							</group>
							<float name="length" value="0" />
							<group name="origin">
								<float name="x" value="0" />
								<float name="y" value="3" />
								<float name="z" value="0" />
							</group>
							<enum name="type" value="default" />
							<template_reference name="weapon_entity_attachment" value="options\attachment_types\entity_create_attachment">
								<template_reference name="entity_attach_data" value="attachments\attach_data_entity">
									<template_reference name="attach_data" value="attachments\attach_data">
										<string name="marker_name_parent" value="" />
										<string name="parent_rigidbody_target_name" value="" />
										<enum name="game_object_attachment_type" value="scenegraph" />
									</template_reference>
									<instance_reference name="ebp" value="ebps\races\core\weapons\wpn_siege_outpost_murder_hole" />
									<group name="attachment_flags">
										<bool name="sim_only" value="False" />
										<bool name="no_pathfinding" value="False" />
										<bool name="not_snappable" value="False" />
										<bool name="restore_snap_to_ground_on_detach" value="False" />
										<bool name="no_sim_update" value="True" />
										<bool name="join_parent_squad" value="False" />
										<bool name="redirect_damage_to_parent_entity" value="True" />
										<bool name="assign_as_attachment_combat_leader" value="False" />
										<bool name="assign_as_attachment_movement_leader" value="False" />
										<bool name="receive_parent_animations" value="False" />
										<bool name="receive_parent_death" value="False" />
									</group>
								</template_reference>
								<list name="possible_blueprint_updates">
								</list>
							</template_reference>
							<template_reference name="non_entity_weapon_wrapper" value="">
							</template_reference>
						</group>
					</list>
					<bool name="receives_attack_commands" value="False" overrideParent="True" />
					<string name="base_marker" value="" />
					<list name="preferred_inventory_item_categories">
					</list>
					<list name="firing_offset_markers">
						<string name="marker" value="fx_muz_murderhole_00" List.ItemID="-1639174320" />
						<string name="marker" value="fx_muz_murderhole_01" List.ItemID="-1851949501" />
						<string name="marker" value="fx_muz_murderhole_02" List.ItemID="986250610" />
					</list>
					<bool name="initialize_weapons_on_creation" value="False" />
					<string name="offhand_marker" value="" />
				</group>
				<group name="hardpoint" comment="Garrison Weapon 1" List.ItemID="1570008390">
					<float name="parent_hardpoint" value="-1" />
					<list name="weapon_table">
						<group name="weapon" List.ItemID="-2033985134">
							<group name="heading">
								<float name="x" value="0" />
								<float name="y" value="0" />
								<float name="z" value="1" />
							</group>
							<float name="length" value="0" />
							<group name="origin">
								<float name="x" value="0" />
								<float name="y" value="0.5" />
								<float name="z" value="0" />
							</group>
							<enum name="type" value="default" />
							<template_reference name="weapon_entity_attachment" value="options\attachment_types\entity_create_attachment">
								<template_reference name="entity_attach_data" value="attachments\attach_data_entity">
									<template_reference name="attach_data" value="attachments\attach_data">
										<string name="marker_name_parent" value="" />
										<string name="parent_rigidbody_target_name" value="" />
										<enum name="game_object_attachment_type" value="scenegraph" />
									</template_reference>
									<instance_reference name="ebp" value="ebps\races\core\weapons\wpn_siege_wooden_fort_arrows_garrison" overrideParent="True" />
									<group name="attachment_flags">
										<bool name="sim_only" value="False" />
										<bool name="no_pathfinding" value="False" />
										<bool name="not_snappable" value="False" />
										<bool name="restore_snap_to_ground_on_detach" value="False" />
										<bool name="no_sim_update" value="False" />
										<bool name="join_parent_squad" value="False" />
										<bool name="redirect_damage_to_parent_entity" value="True" />
										<bool name="assign_as_attachment_combat_leader" value="False" />
										<bool name="assign_as_attachment_movement_leader" value="False" />
										<bool name="receive_parent_animations" value="False" />
										<bool name="receive_parent_death" value="False" />
									</group>
								</template_reference>
								<list name="possible_blueprint_updates">
								</list>
							</template_reference>
							<template_reference name="non_entity_weapon_wrapper" value="">
							</template_reference>
						</group>
					</list>
					<bool name="receives_attack_commands" value="True" />
					<string name="base_marker" value="" />
					<list name="preferred_inventory_item_categories">
					</list>
					<list name="firing_offset_markers" overrideParent="True">
						<string name="marker" value="fx_muz_arrow_00" List.ItemID="476250784" />
						<string name="marker" value="fx_muz_arrow_01" List.ItemID="381782924" />
						<string name="marker" value="fx_muz_arrow_02" List.ItemID="-393051647" />
						<string name="marker" value="fx_muz_arrow_03" List.ItemID="235484954" />
					</list>
					<bool name="initialize_weapons_on_creation" value="False" overrideParent="True" />
					<string name="offhand_marker" value="" />
				</group>
				<group name="hardpoint" comment="Garrison Weapon 2" List.ItemID="-940813266">
					<float name="parent_hardpoint" value="-1" />
					<list name="weapon_table">
						<group name="weapon" List.ItemID="9634202">
							<group name="heading">
								<float name="x" value="0" />
								<float name="y" value="0" />
								<float name="z" value="1" />
							</group>
							<float name="length" value="0" />
							<group name="origin">
								<float name="x" value="0" />
								<float name="y" value="0.5" />
								<float name="z" value="0" />
							</group>
							<enum name="type" value="default" />
							<template_reference name="weapon_entity_attachment" value="options\attachment_types\entity_create_attachment">
								<template_reference name="entity_attach_data" value="attachments\attach_data_entity">
									<template_reference name="attach_data" value="attachments\attach_data">
										<string name="marker_name_parent" value="" />
										<string name="parent_rigidbody_target_name" value="" />
										<enum name="game_object_attachment_type" value="scenegraph" />
									</template_reference>
									<instance_reference name="ebp" value="ebps\races\core\weapons\wpn_siege_wooden_fort_arrows_garrison" overrideParent="True" />
									<group name="attachment_flags">
										<bool name="sim_only" value="False" />
										<bool name="no_pathfinding" value="False" />
										<bool name="not_snappable" value="False" />
										<bool name="restore_snap_to_ground_on_detach" value="False" />
										<bool name="no_sim_update" value="False" />
										<bool name="join_parent_squad" value="False" />
										<bool name="redirect_damage_to_parent_entity" value="True" />
										<bool name="assign_as_attachment_combat_leader" value="False" />
										<bool name="assign_as_attachment_movement_leader" value="False" />
										<bool name="receive_parent_animations" value="False" />
										<bool name="receive_parent_death" value="False" />
									</group>
								</template_reference>
								<list name="possible_blueprint_updates">
								</list>
							</template_reference>
							<template_reference name="non_entity_weapon_wrapper" value="">
							</template_reference>
						</group>
					</list>
					<bool name="receives_attack_commands" value="True" />
					<string name="base_marker" value="" />
					<list name="preferred_inventory_item_categories">
					</list>
					<list name="firing_offset_markers" overrideParent="True">
						<string name="marker" value="fx_muz_arrow_00" List.ItemID="-619508545" />
						<string name="marker" value="fx_muz_arrow_01" List.ItemID="-200112055" />
						<string name="marker" value="fx_muz_arrow_02" List.ItemID="-276280928" />
						<string name="marker" value="fx_muz_arrow_03" List.ItemID="-1210129665" />
					</list>
					<bool name="initialize_weapons_on_creation" value="False" overrideParent="True" />
					<string name="offhand_marker" value="" />
				</group>
				<group name="hardpoint" comment="Garrison Weapon 3" List.ItemID="442482082">
					<float name="parent_hardpoint" value="-1" />
					<list name="weapon_table">
						<group name="weapon" List.ItemID="-486897009">
							<group name="heading">
								<float name="x" value="0" />
								<float name="y" value="0" />
								<float name="z" value="1" />
							</group>
							<float name="length" value="0" />
							<group name="origin">
								<float name="x" value="0" />
								<float name="y" value="0.5" />
								<float name="z" value="0" />
							</group>
							<enum name="type" value="default" />
							<template_reference name="weapon_entity_attachment" value="options\attachment_types\entity_create_attachment">
								<template_reference name="entity_attach_data" value="attachments\attach_data_entity">
									<template_reference name="attach_data" value="attachments\attach_data">
										<string name="marker_name_parent" value="" />
										<string name="parent_rigidbody_target_name" value="" />
										<enum name="game_object_attachment_type" value="scenegraph" />
									</template_reference>
									<instance_reference name="ebp" value="ebps\races\core\weapons\wpn_siege_wooden_fort_arrows_garrison" overrideParent="True" />
									<group name="attachment_flags">
										<bool name="sim_only" value="False" />
										<bool name="no_pathfinding" value="False" />
										<bool name="not_snappable" value="False" />
										<bool name="restore_snap_to_ground_on_detach" value="False" />
										<bool name="no_sim_update" value="False" />
										<bool name="join_parent_squad" value="False" />
										<bool name="redirect_damage_to_parent_entity" value="True" />
										<bool name="assign_as_attachment_combat_leader" value="False" />
										<bool name="assign_as_attachment_movement_leader" value="False" />
										<bool name="receive_parent_animations" value="False" />
										<bool name="receive_parent_death" value="False" />
									</group>
								</template_reference>
								<list name="possible_blueprint_updates">
								</list>
							</template_reference>
							<template_reference name="non_entity_weapon_wrapper" value="">
							</template_reference>
						</group>
					</list>
					<bool name="receives_attack_commands" value="True" />
					<string name="base_marker" value="" />
					<list name="preferred_inventory_item_categories">
					</list>
					<list name="firing_offset_markers" overrideParent="True">
						<string name="marker" value="fx_muz_arrow_00" List.ItemID="1841271320" />
						<string name="marker" value="fx_muz_arrow_01" List.ItemID="1689466919" />
						<string name="marker" value="fx_muz_arrow_02" List.ItemID="-617882738" />
						<string name="marker" value="fx_muz_arrow_03" List.ItemID="442489286" />
					</list>
					<bool name="initialize_weapons_on_creation" value="False" overrideParent="True" />
					<string name="offhand_marker" value="" />
				</group>
				<group name="hardpoint" comment="Garrison Weapon 4&#xD;&#xA;" List.ItemID="1242085611">
					<float name="parent_hardpoint" value="-1" />
					<list name="weapon_table">
						<group name="weapon" List.ItemID="1037055164">
							<group name="heading">
								<float name="x" value="0" />
								<float name="y" value="0" />
								<float name="z" value="1" />
							</group>
							<float name="length" value="0" />
							<group name="origin">
								<float name="x" value="0" />
								<float name="y" value="0.5" />
								<float name="z" value="0" />
							</group>
							<enum name="type" value="default" />
							<template_reference name="weapon_entity_attachment" value="options\attachment_types\entity_create_attachment">
								<template_reference name="entity_attach_data" value="attachments\attach_data_entity">
									<template_reference name="attach_data" value="attachments\attach_data">
										<string name="marker_name_parent" value="" />
										<string name="parent_rigidbody_target_name" value="" />
										<enum name="game_object_attachment_type" value="scenegraph" />
									</template_reference>
									<instance_reference name="ebp" value="ebps\races\core\weapons\wpn_siege_wooden_fort_arrows_garrison" overrideParent="True" />
									<group name="attachment_flags">
										<bool name="sim_only" value="False" />
										<bool name="no_pathfinding" value="False" />
										<bool name="not_snappable" value="False" />
										<bool name="restore_snap_to_ground_on_detach" value="False" />
										<bool name="no_sim_update" value="False" />
										<bool name="join_parent_squad" value="False" />
										<bool name="redirect_damage_to_parent_entity" value="True" />
										<bool name="assign_as_attachment_combat_leader" value="False" />
										<bool name="assign_as_attachment_movement_leader" value="False" />
										<bool name="receive_parent_animations" value="False" />
										<bool name="receive_parent_death" value="False" />
									</group>
								</template_reference>
								<list name="possible_blueprint_updates">
								</list>
							</template_reference>
							<template_reference name="non_entity_weapon_wrapper" value="">
							</template_reference>
						</group>
					</list>
					<bool name="receives_attack_commands" value="True" />
					<string name="base_marker" value="" />
					<list name="preferred_inventory_item_categories">
					</list>
					<list name="firing_offset_markers" overrideParent="True">
						<string name="marker" value="fx_muz_arrow_00" List.ItemID="1959788755" />
						<string name="marker" value="fx_muz_arrow_01" List.ItemID="-916640699" />
						<string name="marker" value="fx_muz_arrow_02" List.ItemID="1787329643" />
						<string name="marker" value="fx_muz_arrow_03" List.ItemID="-1273457755" />
					</list>
					<bool name="initialize_weapons_on_creation" value="False" overrideParent="True" />
					<string name="offhand_marker" value="" />
				</group>
				<group name="hardpoint" comment="Garrison Weapon 5" List.ItemID="-219672893">
					<float name="parent_hardpoint" value="-1" />
					<list name="weapon_table">
						<group name="weapon" List.ItemID="978416378">
							<group name="heading">
								<float name="x" value="0" />
								<float name="y" value="0" />
								<float name="z" value="1" />
							</group>
							<float name="length" value="0" />
							<group name="origin">
								<float name="x" value="0" />
								<float name="y" value="0.5" />
								<float name="z" value="0" />
							</group>
							<enum name="type" value="default" />
							<template_reference name="weapon_entity_attachment" value="options\attachment_types\entity_create_attachment">
								<template_reference name="entity_attach_data" value="attachments\attach_data_entity">
									<template_reference name="attach_data" value="attachments\attach_data">
										<string name="marker_name_parent" value="" />
										<string name="parent_rigidbody_target_name" value="" />
										<enum name="game_object_attachment_type" value="scenegraph" />
									</template_reference>
									<instance_reference name="ebp" value="ebps\races\core\weapons\wpn_siege_wooden_fort_arrows_garrison" overrideParent="True" />
									<group name="attachment_flags">
										<bool name="sim_only" value="False" />
										<bool name="no_pathfinding" value="False" />
										<bool name="not_snappable" value="False" />
										<bool name="restore_snap_to_ground_on_detach" value="False" />
										<bool name="no_sim_update" value="False" />
										<bool name="join_parent_squad" value="False" />
										<bool name="redirect_damage_to_parent_entity" value="True" />
										<bool name="assign_as_attachment_combat_leader" value="False" />
										<bool name="assign_as_attachment_movement_leader" value="False" />
										<bool name="receive_parent_animations" value="False" />
										<bool name="receive_parent_death" value="False" />
									</group>
								</template_reference>
								<list name="possible_blueprint_updates">
								</list>
							</template_reference>
							<template_reference name="non_entity_weapon_wrapper" value="">
							</template_reference>
						</group>
					</list>
					<bool name="receives_attack_commands" value="True" />
					<string name="base_marker" value="" />
					<list name="preferred_inventory_item_categories">
					</list>
					<list name="firing_offset_markers" overrideParent="True">
						<string name="marker" value="fx_muz_arrow_00" List.ItemID="1017432528" />
						<string name="marker" value="fx_muz_arrow_01" List.ItemID="-2063879236" />
						<string name="marker" value="fx_muz_arrow_02" List.ItemID="-47706484" />
						<string name="marker" value="fx_muz_arrow_03" List.ItemID="-76795414" />
					</list>
					<bool name="initialize_weapons_on_creation" value="False" overrideParent="True" />
					<string name="offhand_marker" value="" />
				</group>
				<group name="hardpoint" comment="Garrison Weapon 6" List.ItemID="-694446669">
					<float name="parent_hardpoint" value="-1" />
					<list name="weapon_table">
						<group name="weapon" List.ItemID="-1828091297">
							<group name="heading">
								<float name="x" value="0" />
								<float name="y" value="0" />
								<float name="z" value="1" />
							</group>
							<float name="length" value="0" />
							<group name="origin">
								<float name="x" value="0" />
								<float name="y" value="0.5" />
								<float name="z" value="0" />
							</group>
							<enum name="type" value="default" />
							<template_reference name="weapon_entity_attachment" value="options\attachment_types\entity_create_attachment">
								<template_reference name="entity_attach_data" value="attachments\attach_data_entity">
									<template_reference name="attach_data" value="attachments\attach_data">
										<string name="marker_name_parent" value="" />
										<string name="parent_rigidbody_target_name" value="" />
										<enum name="game_object_attachment_type" value="scenegraph" />
									</template_reference>
									<instance_reference name="ebp" value="ebps\races\core\weapons\wpn_siege_wooden_fort_arrows_garrison" overrideParent="True" />
									<group name="attachment_flags">
										<bool name="sim_only" value="False" />
										<bool name="no_pathfinding" value="False" />
										<bool name="not_snappable" value="False" />
										<bool name="restore_snap_to_ground_on_detach" value="False" />
										<bool name="no_sim_update" value="False" />
										<bool name="join_parent_squad" value="False" />
										<bool name="redirect_damage_to_parent_entity" value="True" />
										<bool name="assign_as_attachment_combat_leader" value="False" />
										<bool name="assign_as_attachment_movement_leader" value="False" />
										<bool name="receive_parent_animations" value="False" />
										<bool name="receive_parent_death" value="False" />
									</group>
								</template_reference>
								<list name="possible_blueprint_updates">
								</list>
							</template_reference>
							<template_reference name="non_entity_weapon_wrapper" value="">
							</template_reference>
						</group>
					</list>
					<bool name="receives_attack_commands" value="True" />
					<string name="base_marker" value="" />
					<list name="preferred_inventory_item_categories">
					</list>
					<list name="firing_offset_markers" overrideParent="True">
						<string name="marker" value="fx_muz_arrow_00" List.ItemID="884881721" />
						<string name="marker" value="fx_muz_arrow_01" List.ItemID="-447322645" />
						<string name="marker" value="fx_muz_arrow_02" List.ItemID="-917576504" />
						<string name="marker" value="fx_muz_arrow_03" List.ItemID="1354816170" />
					</list>
					<bool name="initialize_weapons_on_creation" value="False" overrideParent="True" />
					<string name="offhand_marker" value="" />
				</group>
				<group name="hardpoint" comment="Garrison Weapon 7" List.ItemID="-1880768050">
					<float name="parent_hardpoint" value="-1" />
					<list name="weapon_table">
						<group name="weapon" List.ItemID="1779489157">
							<group name="heading">
								<float name="x" value="0" />
								<float name="y" value="0" />
								<float name="z" value="1" />
							</group>
							<float name="length" value="0" />
							<group name="origin">
								<float name="x" value="0" />
								<float name="y" value="0.5" />
								<float name="z" value="0" />
							</group>
							<enum name="type" value="default" />
							<template_reference name="weapon_entity_attachment" value="options\attachment_types\entity_create_attachment">
								<template_reference name="entity_attach_data" value="attachments\attach_data_entity">
									<template_reference name="attach_data" value="attachments\attach_data">
										<string name="marker_name_parent" value="" />
										<string name="parent_rigidbody_target_name" value="" />
										<enum name="game_object_attachment_type" value="scenegraph" />
									</template_reference>
									<instance_reference name="ebp" value="ebps\races\core\weapons\wpn_siege_wooden_fort_arrows_garrison" overrideParent="True" />
									<group name="attachment_flags">
										<bool name="sim_only" value="False" />
										<bool name="no_pathfinding" value="False" />
										<bool name="not_snappable" value="False" />
										<bool name="restore_snap_to_ground_on_detach" value="False" />
										<bool name="no_sim_update" value="False" />
										<bool name="join_parent_squad" value="False" />
										<bool name="redirect_damage_to_parent_entity" value="True" />
										<bool name="assign_as_attachment_combat_leader" value="False" />
										<bool name="assign_as_attachment_movement_leader" value="False" />
										<bool name="receive_parent_animations" value="False" />
										<bool name="receive_parent_death" value="False" />
									</group>
								</template_reference>
								<list name="possible_blueprint_updates">
								</list>
							</template_reference>
							<template_reference name="non_entity_weapon_wrapper" value="">
							</template_reference>
						</group>
					</list>
					<bool name="receives_attack_commands" value="True" />
					<string name="base_marker" value="" />
					<list name="preferred_inventory_item_categories">
					</list>
					<list name="firing_offset_markers" overrideParent="True">
						<string name="marker" value="fx_muz_arrow_00" List.ItemID="-303958798" />
						<string name="marker" value="fx_muz_arrow_01" List.ItemID="1355203559" />
						<string name="marker" value="fx_muz_arrow_02" List.ItemID="1629970054" />
						<string name="marker" value="fx_muz_arrow_03" List.ItemID="562315246" />
					</list>
					<bool name="initialize_weapons_on_creation" value="False" overrideParent="True" />
					<string name="offhand_marker" value="" />
				</group>
				<group name="hardpoint" comment="Garrison Weapon 8" List.ItemID="-660956297">
					<float name="parent_hardpoint" value="-1" />
					<list name="weapon_table">
						<group name="weapon" List.ItemID="1029051556">
							<group name="heading">
								<float name="x" value="0" />
								<float name="y" value="0" />
								<float name="z" value="1" />
							</group>
							<float name="length" value="0" />
							<group name="origin">
								<float name="x" value="0" />
								<float name="y" value="0.5" />
								<float name="z" value="0" />
							</group>
							<enum name="type" value="default" />
							<template_reference name="weapon_entity_attachment" value="options\attachment_types\entity_create_attachment">
								<template_reference name="entity_attach_data" value="attachments\attach_data_entity">
									<template_reference name="attach_data" value="attachments\attach_data">
										<string name="marker_name_parent" value="" />
										<string name="parent_rigidbody_target_name" value="" />
										<enum name="game_object_attachment_type" value="scenegraph" />
									</template_reference>
									<instance_reference name="ebp" value="ebps\races\core\weapons\wpn_siege_wooden_fort_arrows_garrison" overrideParent="True" />
									<group name="attachment_flags">
										<bool name="sim_only" value="False" />
										<bool name="no_pathfinding" value="False" />
										<bool name="not_snappable" value="False" />
										<bool name="restore_snap_to_ground_on_detach" value="False" />
										<bool name="no_sim_update" value="False" />
										<bool name="join_parent_squad" value="False" />
										<bool name="redirect_damage_to_parent_entity" value="True" />
										<bool name="assign_as_attachment_combat_leader" value="False" />
										<bool name="assign_as_attachment_movement_leader" value="False" />
										<bool name="receive_parent_animations" value="False" />
										<bool name="receive_parent_death" value="False" />
									</group>
								</template_reference>
								<list name="possible_blueprint_updates">
								</list>
							</template_reference>
							<template_reference name="non_entity_weapon_wrapper" value="">
							</template_reference>
						</group>
					</list>
					<bool name="receives_attack_commands" value="True" />
					<string name="base_marker" value="" />
					<list name="preferred_inventory_item_categories">
					</list>
					<list name="firing_offset_markers" overrideParent="True">
						<string name="marker" value="fx_muz_arrow_00" List.ItemID="-649229557" />
						<string name="marker" value="fx_muz_arrow_01" List.ItemID="-1441644564" />
						<string name="marker" value="fx_muz_arrow_02" List.ItemID="-1653593304" />
						<string name="marker" value="fx_muz_arrow_03" List.ItemID="1943771556" />
					</list>
					<bool name="initialize_weapons_on_creation" value="False" overrideParent="True" />
					<string name="offhand_marker" value="" />
				</group>
			</list>
		</template_reference>
		<template_reference name="exts" value="ebpextensions\hold_ext" List.ItemID="-773066302" List.ParentItemID="-773066302">
			<float name="num_slots" value="8" overrideParent="True" />
			<float name="num_squad_slots" value="8" overrideParent="True" />
		</template_reference>
		<template_reference name="exts" value="ebpextensions\ability_ext" List.ItemID="-589861990" List.ParentItemID="-589861990">
			<list name="abilities" overrideParent="True">
				<instance_reference name="ability" value="abilities\timed_abilities\civ_core\core_building_scuttle" List.ItemID="-986776564" />
				<instance_reference name="ability" value="abilities\modal_abilities\core\town_bell\hold_return_to_work" List.ItemID="-989877954" />
				<instance_reference name="ability" value="abilities\always_on_abilities\rus\wooden_fortress_influence_rus" List.ItemID="1077890475" />
			</list>
		</template_reference>
		<template_reference name="exts" value="ebpextensions\district_generator_ext" List.ItemID="700444599" List.ListAction="Append">
			<float name="range_metres" value="12" overrideParent="True" />
			<int name="generator_value" value="0" />
			<bool name="disable_generation_on_spawn" value="False" />
			<bool name="is_root_generator" value="True" />
			<int name="district_palette_id" value="1" />
			<list name="requirements">
			</list>
		</template_reference>
	</list>
	<uniqueid name="pbgid" value="133438" />
	<instance_reference name="parent_pbg" value="ebps\races\core\buildings\building_defense_outpost" />
	<variant name="campaign">
		<list name="extensions">
			<template_reference name="exts" value="ebpextensions\entity_blueprint_ext" List.ItemID="-1097396820" List.ParentItemID="-1097396820">
				<instance_reference name="animator_attachments" value="attachments\attachment_lists\civilizations\rus\buildings\defense_wooden_fort_rus\defense_wooden_fort_rus" overrideParent="True" />
				<bool name="browsable_in_editor" value="True" overrideParent="True" />
			</template_reference>
			<template_reference name="exts" value="ebpextensions\cost_ext" overrideParent="True" List.ItemID="160608707" List.ParentItemID="160608707">
				<group name="time_cost">
					<enum_table name="cost">
						<float name="action" value="0" />
						<float name="popcap" value="0" />
						<float name="command" value="0" />
						<float name="food" value="0" />
						<float name="wood" value="175" overrideParent="True" />
						<float name="stone" value="0" />
						<float name="gold" value="0" />
						<float name="militia_hre" value="0" />
						<float name="merc_byz" value="0" />
					</enum_table>
					<float name="time_seconds" value="50" />
					<int name="time_turns" value="0" />
				</group>
			</template_reference>
			<template_reference name="exts" value="ebpextensions\health_ext" List.ItemID="2095670651" List.ParentItemID="2095670651">
				<float name="hitpoints" value="2500" overrideParent="True" />
			</template_reference>
			<template_reference name="exts" value="ebpextensions\sight_ext" List.ItemID="-1847896003" List.ParentItemID="-1847896003">
				<group name="sight_package">
					<float name="inner_radius" value="35" overrideParent="True" />
				</group>
			</template_reference>
			<template_reference name="exts" value="ebpextensions\type_ext" List.ItemID="-1052651549" List.ParentItemID="-1052651549">
				<list name="unit_type_list" overrideParent="True">
					<enum name="unit_type" value="military" List.ItemID="312488465" />
					<enum name="unit_type" value="building" List.ItemID="-1766370378" />
					<enum name="unit_type" value="tower" List.ItemID="1930970213" />
					<enum name="unit_type" value="outpost" List.ItemID="-66121970" />
					<enum name="unit_type" value="defensive_structure" List.ItemID="1126399330" />
					<enum name="unit_type" value="siegeable" List.ItemID="1106420891" />
					<enum name="unit_type" value="town_bell_target" List.ItemID="1915016763" />
					<enum name="unit_type" value="scar_outpost" overrideParent="True" List.ItemID="-786961857" />
					<enum name="unit_type" value="has_default_building_weapons" List.ItemID="1926423838" />
					<enum name="unit_type" value="wooden_fortress" List.ItemID="1834914189" />
				</list>
				<list name="race_type_list" overrideParent="True">
					<instance_reference name="race_type" value="racebps\rus" List.ItemID="929033805" />
				</list>
			</template_reference>
			<template_reference name="exts" value="ebpextensions\ui_ext" List.ItemID="1841931908" List.ParentItemID="1841931908">
				<file name="icon_name" value="races\rus\buildings\wooden_fortress" overrideParent="True" />
				<bool name="is_unique_to_race" value="True" overrideParent="True" />
				<group name="ui_codex_info">
					<bool name="exclusive" value="True" overrideParent="True" />
				</group>
				<list name="ui_extra_infos" overrideParent="True">
					<template_reference name="ui_extra_info" value="info\ui_extra_info" List.ItemID="986520520">
						<file name="icon" value="influence_buff" overrideParent="True" />
						<locstring name="description" value="11191462" />
						<template_reference name="description_formatter" value="">
						</template_reference>
					</template_reference>
				</list>
				<string name="telemetry_name" value="Wooden Fortress" overrideParent="True" />
			</template_reference>
			<template_reference name="exts" value="ebpextensions\upgrade_ext" List.ItemID="-1230187710" List.ParentItemID="-1230187710">
				<list name="standard_upgrades" overrideParent="True">
					<instance_reference name="upgrade" value="upgrade\races\rus\research\upgrade_wooden_castle_arrowslits_rus" overrideParent="True" List.ItemID="-1191556877" />
					<instance_reference name="upgrade" value="upgrade\races\rus\research\upgrade_wooden_castle_turret_rus" List.ItemID="-1499438194" />
					<instance_reference name="upgrade" value="upgrade\races\rus\research\upgrade_wooden_castle_watch_rus" List.ItemID="-2085063230" />
					<instance_reference name="upgrade" value="upgrade\races\rus\research\upgrade_wooden_castle_springald_rus" List.ItemID="-1798455998" />
				</list>
			</template_reference>
			<template_reference name="exts" value="ebpextensions\site_ext" List.ItemID="1466097282" List.ParentItemID="1466097282">
				<bool name="snap_to_construction_grid" value="True" overrideParent="True" />
			</template_reference>
			<template_reference name="exts" value="ebpextensions\construction_ext" List.ItemID="1545136981" List.ParentItemID="1545136981">
				<group name="on_construction_complete_state_tree_refs">
					<string name="while_construction_complete_entity_state_tree_ref" value="building_construction_complete\buildings\outpost_construction_complete" overrideParent="True" />
				</group>
				<bool name="construction_site_erase_inactive" value="False" overrideParent="True" />
			</template_reference>
			<template_reference name="exts" value="ebpextensions\spawner_ext" List.ItemID="366977626" List.ParentItemID="366977626">
				<instance_reference name="rally_pass_type" value="pass_types\infantry" overrideParent="True" />
			</template_reference>
			<template_reference name="exts" value="ebpextensions\burn_ext" List.ItemID="-1634687319" List.ParentItemID="-1634687319">
				<float name="on_fire_damage_per_sec" value="12" overrideParent="True" />
			</template_reference>
			<template_reference name="exts" value="ebpextensions\combat_ext" List.ItemID="412599691" List.ParentItemID="412599691">
				<list name="hardpoints" overrideParent="True">
					<group name="hardpoint" comment="Arrowslits Slot" List.ItemID="19483340">
						<float name="parent_hardpoint" value="-1" />
						<list name="weapon_table">
							<group name="weapon" List.ItemID="-806328897">
								<group name="heading">
									<float name="x" value="0" />
									<float name="y" value="0.3" />
									<float name="z" value="1" />
								</group>
								<float name="length" value="0" />
								<group name="origin">
									<float name="x" value="0" />
									<float name="y" value="6" />
									<float name="z" value="0" />
								</group>
								<enum name="type" value="default" />
								<template_reference name="weapon_entity_attachment" value="options\attachment_types\entity_create_attachment">
									<template_reference name="entity_attach_data" value="attachments\attach_data_entity">
										<template_reference name="attach_data" value="attachments\attach_data">
											<string name="marker_name_parent" value="" />
											<string name="parent_rigidbody_target_name" value="" />
											<enum name="game_object_attachment_type" value="scenegraph" />
										</template_reference>
										<instance_reference name="ebp" value="ebps\races\core\weapons\wpn_siege_outpost_arrows" />
										<group name="attachment_flags">
											<bool name="sim_only" value="False" />
											<bool name="no_pathfinding" value="False" />
											<bool name="not_snappable" value="False" />
											<bool name="restore_snap_to_ground_on_detach" value="False" />
											<bool name="no_sim_update" value="True" />
											<bool name="join_parent_squad" value="False" />
											<bool name="redirect_damage_to_parent_entity" value="True" />
											<bool name="assign_as_attachment_combat_leader" value="False" />
											<bool name="assign_as_attachment_movement_leader" value="False" />
											<bool name="receive_parent_animations" value="False" />
											<bool name="receive_parent_death" value="False" />
										</group>
									</template_reference>
									<list name="possible_blueprint_updates">
									</list>
								</template_reference>
								<template_reference name="non_entity_weapon_wrapper" value="">
								</template_reference>
							</group>
						</list>
						<bool name="receives_attack_commands" value="True" />
						<string name="base_marker" value="" />
						<list name="preferred_inventory_item_categories">
						</list>
						<list name="firing_offset_markers">
							<string name="marker" value="fx_muz_arrow_00" List.ItemID="795278843" />
							<string name="marker" value="fx_muz_arrow_01" List.ItemID="-1898100820" />
							<string name="marker" value="fx_muz_arrow_02" List.ItemID="-95293590" />
							<string name="marker" value="fx_muz_arrow_03" List.ItemID="-1533629831" />
						</list>
						<bool name="initialize_weapons_on_creation" value="False" />
						<string name="offhand_marker" value="" />
					</group>
					<group name="hardpoint" comment="Springald Slot" List.ItemID="-2073855775">
						<float name="parent_hardpoint" value="-1" />
						<list name="weapon_table">
							<group name="weapon" List.ItemID="105723265">
								<group name="heading">
									<float name="x" value="0" />
									<float name="y" value="0" />
									<float name="z" value="1" />
								</group>
								<float name="length" value="0" />
								<group name="origin">
									<float name="x" value="0" />
									<float name="y" value="0.5" />
									<float name="z" value="0" />
								</group>
								<enum name="type" value="default" />
								<template_reference name="weapon_entity_attachment" value="options\attachment_types\entity_create_attachment">
									<template_reference name="entity_attach_data" value="attachments\attach_data_entity">
										<template_reference name="attach_data" value="attachments\attach_data">
											<string name="marker_name_parent" value="" />
											<string name="parent_rigidbody_target_name" value="" />
											<enum name="game_object_attachment_type" value="scenegraph" />
										</template_reference>
										<instance_reference name="ebp" value="ebps\races\rus\weapons\wpn_range_wooden_fort_springald_a_rus" overrideParent="True" />
										<group name="attachment_flags">
											<bool name="sim_only" value="False" />
											<bool name="no_pathfinding" value="False" />
											<bool name="not_snappable" value="False" />
											<bool name="restore_snap_to_ground_on_detach" value="False" />
											<bool name="no_sim_update" value="False" />
											<bool name="join_parent_squad" value="False" />
											<bool name="redirect_damage_to_parent_entity" value="True" />
											<bool name="assign_as_attachment_combat_leader" value="False" />
											<bool name="assign_as_attachment_movement_leader" value="False" />
											<bool name="receive_parent_animations" value="False" />
											<bool name="receive_parent_death" value="False" />
										</group>
									</template_reference>
									<list name="possible_blueprint_updates">
									</list>
								</template_reference>
								<template_reference name="non_entity_weapon_wrapper" value="">
								</template_reference>
							</group>
						</list>
						<bool name="receives_attack_commands" value="True" overrideParent="True" />
						<string name="base_marker" value="" />
						<list name="preferred_inventory_item_categories">
						</list>
						<list name="firing_offset_markers">
						</list>
						<bool name="initialize_weapons_on_creation" value="False" overrideParent="True" />
						<string name="offhand_marker" value="" />
					</group>
					<group name="hardpoint" comment="Springald Slot - District Bonus" List.ItemID="674171328">
						<float name="parent_hardpoint" value="-1" />
						<list name="weapon_table">
							<group name="weapon" List.ItemID="1759843920">
								<group name="heading">
									<float name="x" value="0" />
									<float name="y" value="0" />
									<float name="z" value="1" />
								</group>
								<float name="length" value="0" />
								<group name="origin">
									<float name="x" value="0" />
									<float name="y" value="0.5" />
									<float name="z" value="0" />
								</group>
								<enum name="type" value="default" />
								<template_reference name="weapon_entity_attachment" value="options\attachment_types\entity_create_attachment">
									<template_reference name="entity_attach_data" value="attachments\attach_data_entity">
										<template_reference name="attach_data" value="attachments\attach_data">
											<string name="marker_name_parent" value="" />
											<string name="parent_rigidbody_target_name" value="" />
											<enum name="game_object_attachment_type" value="scenegraph" />
										</template_reference>
										<instance_reference name="ebp" value="ebps\races\rus\weapons\wpn_range_wooden_fort_springald_b_rus" overrideParent="True" />
										<group name="attachment_flags">
											<bool name="sim_only" value="False" />
											<bool name="no_pathfinding" value="False" />
											<bool name="not_snappable" value="False" />
											<bool name="restore_snap_to_ground_on_detach" value="False" />
											<bool name="no_sim_update" value="False" />
											<bool name="join_parent_squad" value="False" />
											<bool name="redirect_damage_to_parent_entity" value="True" />
											<bool name="assign_as_attachment_combat_leader" value="False" />
											<bool name="assign_as_attachment_movement_leader" value="False" />
											<bool name="receive_parent_animations" value="False" />
											<bool name="receive_parent_death" value="False" />
										</group>
									</template_reference>
									<list name="possible_blueprint_updates">
									</list>
								</template_reference>
								<template_reference name="non_entity_weapon_wrapper" value="">
								</template_reference>
							</group>
						</list>
						<bool name="receives_attack_commands" value="True" overrideParent="True" />
						<string name="base_marker" value="" />
						<list name="preferred_inventory_item_categories">
						</list>
						<list name="firing_offset_markers">
						</list>
						<bool name="initialize_weapons_on_creation" value="False" overrideParent="True" />
						<string name="offhand_marker" value="" />
					</group>
					<group name="hardpoint" comment="Murderholes Slot" List.ItemID="1424367183">
						<float name="parent_hardpoint" value="-1" />
						<list name="weapon_table">
							<group name="weapon" List.ItemID="1266332283">
								<group name="heading">
									<float name="x" value="0" />
									<float name="y" value="0" />
									<float name="z" value="1" />
								</group>
								<float name="length" value="0" />
								<group name="origin">
									<float name="x" value="0" />
									<float name="y" value="3" />
									<float name="z" value="0" />
								</group>
								<enum name="type" value="default" />
								<template_reference name="weapon_entity_attachment" value="options\attachment_types\entity_create_attachment">
									<template_reference name="entity_attach_data" value="attachments\attach_data_entity">
										<template_reference name="attach_data" value="attachments\attach_data">
											<string name="marker_name_parent" value="" />
											<string name="parent_rigidbody_target_name" value="" />
											<enum name="game_object_attachment_type" value="scenegraph" />
										</template_reference>
										<instance_reference name="ebp" value="ebps\races\core\weapons\wpn_siege_outpost_murder_hole" />
										<group name="attachment_flags">
											<bool name="sim_only" value="False" />
											<bool name="no_pathfinding" value="False" />
											<bool name="not_snappable" value="False" />
											<bool name="restore_snap_to_ground_on_detach" value="False" />
											<bool name="no_sim_update" value="True" />
											<bool name="join_parent_squad" value="False" />
											<bool name="redirect_damage_to_parent_entity" value="True" />
											<bool name="assign_as_attachment_combat_leader" value="False" />
											<bool name="assign_as_attachment_movement_leader" value="False" />
											<bool name="receive_parent_animations" value="False" />
											<bool name="receive_parent_death" value="False" />
										</group>
									</template_reference>
									<list name="possible_blueprint_updates">
									</list>
								</template_reference>
								<template_reference name="non_entity_weapon_wrapper" value="">
								</template_reference>
							</group>
						</list>
						<bool name="receives_attack_commands" value="False" overrideParent="True" />
						<string name="base_marker" value="" />
						<list name="preferred_inventory_item_categories">
						</list>
						<list name="firing_offset_markers">
							<string name="marker" value="fx_muz_murderhole_00" List.ItemID="-899306661" />
							<string name="marker" value="fx_muz_murderhole_01" List.ItemID="483611231" />
							<string name="marker" value="fx_muz_murderhole_02" List.ItemID="-458913043" />
						</list>
						<bool name="initialize_weapons_on_creation" value="False" />
						<string name="offhand_marker" value="" />
					</group>
					<group name="hardpoint" comment="Garrison Weapon 1" List.ItemID="-207811440">
						<float name="parent_hardpoint" value="-1" />
						<list name="weapon_table">
							<group name="weapon" List.ItemID="1584116739">
								<group name="heading">
									<float name="x" value="0" />
									<float name="y" value="0" />
									<float name="z" value="1" />
								</group>
								<float name="length" value="0" />
								<group name="origin">
									<float name="x" value="0" />
									<float name="y" value="0.5" />
									<float name="z" value="0" />
								</group>
								<enum name="type" value="default" />
								<template_reference name="weapon_entity_attachment" value="options\attachment_types\entity_create_attachment">
									<template_reference name="entity_attach_data" value="attachments\attach_data_entity">
										<template_reference name="attach_data" value="attachments\attach_data">
											<string name="marker_name_parent" value="" />
											<string name="parent_rigidbody_target_name" value="" />
											<enum name="game_object_attachment_type" value="scenegraph" />
										</template_reference>
										<instance_reference name="ebp" value="ebps\races\core\weapons\wpn_siege_wooden_fort_arrows_garrison" overrideParent="True" />
										<group name="attachment_flags">
											<bool name="sim_only" value="False" />
											<bool name="no_pathfinding" value="False" />
											<bool name="not_snappable" value="False" />
											<bool name="restore_snap_to_ground_on_detach" value="False" />
											<bool name="no_sim_update" value="False" />
											<bool name="join_parent_squad" value="False" />
											<bool name="redirect_damage_to_parent_entity" value="True" />
											<bool name="assign_as_attachment_combat_leader" value="False" />
											<bool name="assign_as_attachment_movement_leader" value="False" />
											<bool name="receive_parent_animations" value="False" />
											<bool name="receive_parent_death" value="False" />
										</group>
									</template_reference>
									<list name="possible_blueprint_updates">
									</list>
								</template_reference>
								<template_reference name="non_entity_weapon_wrapper" value="">
								</template_reference>
							</group>
						</list>
						<bool name="receives_attack_commands" value="True" />
						<string name="base_marker" value="" />
						<list name="preferred_inventory_item_categories">
						</list>
						<list name="firing_offset_markers">
						</list>
						<bool name="initialize_weapons_on_creation" value="False" overrideParent="True" />
						<string name="offhand_marker" value="" />
					</group>
					<group name="hardpoint" comment="Garrison Weapon 2" List.ItemID="1272869483">
						<float name="parent_hardpoint" value="-1" />
						<list name="weapon_table">
							<group name="weapon" List.ItemID="1204965803">
								<group name="heading">
									<float name="x" value="0" />
									<float name="y" value="0" />
									<float name="z" value="1" />
								</group>
								<float name="length" value="0" />
								<group name="origin">
									<float name="x" value="0" />
									<float name="y" value="0.5" />
									<float name="z" value="0" />
								</group>
								<enum name="type" value="default" />
								<template_reference name="weapon_entity_attachment" value="options\attachment_types\entity_create_attachment">
									<template_reference name="entity_attach_data" value="attachments\attach_data_entity">
										<template_reference name="attach_data" value="attachments\attach_data">
											<string name="marker_name_parent" value="" />
											<string name="parent_rigidbody_target_name" value="" />
											<enum name="game_object_attachment_type" value="scenegraph" />
										</template_reference>
										<instance_reference name="ebp" value="ebps\races\core\weapons\wpn_siege_wooden_fort_arrows_garrison" overrideParent="True" />
										<group name="attachment_flags">
											<bool name="sim_only" value="False" />
											<bool name="no_pathfinding" value="False" />
											<bool name="not_snappable" value="False" />
											<bool name="restore_snap_to_ground_on_detach" value="False" />
											<bool name="no_sim_update" value="False" />
											<bool name="join_parent_squad" value="False" />
											<bool name="redirect_damage_to_parent_entity" value="True" />
											<bool name="assign_as_attachment_combat_leader" value="False" />
											<bool name="assign_as_attachment_movement_leader" value="False" />
											<bool name="receive_parent_animations" value="False" />
											<bool name="receive_parent_death" value="False" />
										</group>
									</template_reference>
									<list name="possible_blueprint_updates">
									</list>
								</template_reference>
								<template_reference name="non_entity_weapon_wrapper" value="">
								</template_reference>
							</group>
						</list>
						<bool name="receives_attack_commands" value="True" />
						<string name="base_marker" value="" />
						<list name="preferred_inventory_item_categories">
						</list>
						<list name="firing_offset_markers">
						</list>
						<bool name="initialize_weapons_on_creation" value="False" overrideParent="True" />
						<string name="offhand_marker" value="" />
					</group>
					<group name="hardpoint" comment="Garrison Weapon 3" List.ItemID="1523621149">
						<float name="parent_hardpoint" value="-1" />
						<list name="weapon_table">
							<group name="weapon" List.ItemID="2129541878">
								<group name="heading">
									<float name="x" value="0" />
									<float name="y" value="0" />
									<float name="z" value="1" />
								</group>
								<float name="length" value="0" />
								<group name="origin">
									<float name="x" value="0" />
									<float name="y" value="0.5" />
									<float name="z" value="0" />
								</group>
								<enum name="type" value="default" />
								<template_reference name="weapon_entity_attachment" value="options\attachment_types\entity_create_attachment">
									<template_reference name="entity_attach_data" value="attachments\attach_data_entity">
										<template_reference name="attach_data" value="attachments\attach_data">
											<string name="marker_name_parent" value="" />
											<string name="parent_rigidbody_target_name" value="" />
											<enum name="game_object_attachment_type" value="scenegraph" />
										</template_reference>
										<instance_reference name="ebp" value="ebps\races\core\weapons\wpn_siege_wooden_fort_arrows_garrison" overrideParent="True" />
										<group name="attachment_flags">
											<bool name="sim_only" value="False" />
											<bool name="no_pathfinding" value="False" />
											<bool name="not_snappable" value="False" />
											<bool name="restore_snap_to_ground_on_detach" value="False" />
											<bool name="no_sim_update" value="False" />
											<bool name="join_parent_squad" value="False" />
											<bool name="redirect_damage_to_parent_entity" value="True" />
											<bool name="assign_as_attachment_combat_leader" value="False" />
											<bool name="assign_as_attachment_movement_leader" value="False" />
											<bool name="receive_parent_animations" value="False" />
											<bool name="receive_parent_death" value="False" />
										</group>
									</template_reference>
									<list name="possible_blueprint_updates">
									</list>
								</template_reference>
								<template_reference name="non_entity_weapon_wrapper" value="">
								</template_reference>
							</group>
						</list>
						<bool name="receives_attack_commands" value="True" />
						<string name="base_marker" value="" />
						<list name="preferred_inventory_item_categories">
						</list>
						<list name="firing_offset_markers">
						</list>
						<bool name="initialize_weapons_on_creation" value="False" overrideParent="True" />
						<string name="offhand_marker" value="" />
					</group>
				</list>
			</template_reference>
			<template_reference name="exts" value="ebpextensions\ability_ext" List.ItemID="-1837452725" List.ParentItemID="-1837452725">
				<list name="abilities" overrideParent="True">
					<instance_reference name="ability" value="abilities\timed_abilities\civ_core\core_building_scuttle" List.ItemID="1531023836" />
					<instance_reference name="ability" value="abilities\modal_abilities\core\town_bell\hold_return_to_work" List.ItemID="394024458" />
					<instance_reference name="ability" value="abilities\always_on_abilities\rus\wooden_fortress_influence_rus" List.ItemID="172489280" />
				</list>
			</template_reference>
			<template_reference name="exts" value="ebpextensions\district_generator_ext" List.ItemID="-295392397" List.ListAction="Append">
				<float name="range_metres" value="12" overrideParent="True" />
				<int name="generator_value" value="0" />
				<bool name="disable_generation_on_spawn" value="False" />
				<bool name="is_root_generator" value="True" />
				<int name="district_palette_id" value="1" />
				<list name="requirements">
				</list>
			</template_reference>
		</list>
		<uniqueid name="pbgid" value="133438" />
		<instance_reference name="parent_pbg" value="ebps\races\core\buildings\building_defense_outpost" />
	</variant>
	<variant name="hre_brawl">
		<list name="extensions" removedIds="-1218905965, -773066302, -1966667964">
			<template_reference name="exts" value="ebpextensions\entity_blueprint_ext" List.ItemID="1544196321" List.ParentItemID="1544196321">
				<instance_reference name="animator_attachments" value="attachments\attachment_lists\civilizations\rus\buildings\defense_wooden_fort_rus\defense_wooden_fort_rus" overrideParent="True" />
				<bool name="browsable_in_editor" value="True" overrideParent="True" />
			</template_reference>
			<template_reference name="exts" value="ebpextensions\cost_ext" overrideParent="True" List.ItemID="-1618369463" List.ParentItemID="-1618369463">
				<group name="time_cost">
					<enum_table name="cost">
						<float name="action" value="0" />
						<float name="popcap" value="0" />
						<float name="command" value="0" />
						<float name="food" value="0" />
						<float name="wood" value="175" overrideParent="True" />
						<float name="stone" value="0" />
						<float name="gold" value="0" />
						<float name="militia_hre" value="0" />
						<float name="merc_byz" value="0" />
					</enum_table>
					<float name="time_seconds" value="60" overrideParent="True" />
					<int name="time_turns" value="0" />
				</group>
			</template_reference>
			<template_reference name="exts" value="ebpextensions\health_ext" List.ItemID="2017155034" List.ParentItemID="2017155034">
				<float name="hitpoints" value="750" overrideParent="True" />
				<enum_table name="armor_scaler_by_damage_type">
					<float name="Ranged" value="0" overrideParent="True" />
				</enum_table>
			</template_reference>
			<template_reference name="exts" value="ebpextensions\sight_ext" List.ItemID="462979593" List.ParentItemID="462979593">
				<group name="sight_package" overrideParent="True">
					<float name="inner_radius" value="44" overrideParent="True" />
					<float name="inner_height" value="501" />
					<float name="outer_height" value="-20" />
					<float name="outer_radius" value="44" overrideParent="True" />
					<float name="cone_angle" value="360" />
					<float name="cone_start_radius" value="0" />
				</group>
			</template_reference>
			<template_reference name="exts" value="ebpextensions\type_ext" List.ItemID="-33111220" List.ParentItemID="-33111220">
				<list name="unit_type_list" overrideParent="True">
					<enum name="unit_type" value="military" List.ItemID="-1106423277" />
					<enum name="unit_type" value="building" List.ItemID="-1690735220" />
					<enum name="unit_type" value="tower" List.ItemID="-415984634" />
					<enum name="unit_type" value="outpost" List.ItemID="-1656310824" />
					<enum name="unit_type" value="defensive_structure" List.ItemID="-551281606" />
					<enum name="unit_type" value="siegeable" List.ItemID="1186663544" />
					<enum name="unit_type" value="town_bell_target" List.ItemID="1487947430" />
					<enum name="unit_type" value="scar_outpost" overrideParent="True" List.ItemID="39004540" />
					<enum name="unit_type" value="has_default_building_weapons" List.ItemID="890400294" />
					<enum name="unit_type" value="wooden_fortress" List.ItemID="-1752444433" />
				</list>
				<list name="race_type_list" overrideParent="True">
					<instance_reference name="race_type" value="racebps\rus" List.ItemID="1808068849" />
				</list>
			</template_reference>
			<template_reference name="exts" value="ebpextensions\ui_ext" List.ItemID="-1221151512" List.ParentItemID="-1221151512">
				<file name="icon_name" value="races\rus\buildings\wooden_fortress" overrideParent="True" />
				<bool name="is_unique_to_race" value="False" overrideParent="True" />
				<group name="ui_codex_info">
					<bool name="exclusive" value="True" overrideParent="True" />
				</group>
				<list name="ui_extra_infos" overrideParent="True">
				</list>
				<string name="telemetry_name" value="Wooden Fortress" overrideParent="True" />
				<float name="minimap_icon_scale" value="0.3" overrideParent="True" />
				<file name="minimap_icon" value="minimap\landmark" overrideParent="True" />
				<bool name="use_construction_range_on_selection" value="False" overrideParent="True" />
				<enum name="map_mark" value="" overrideParent="True" />
				<string name="selection_group" value="wooden_fortress" overrideParent="True" />
				<float name="minimap_icon_zoom_scale" value="1" overrideParent="True" />
			</template_reference>
			<template_reference name="exts" value="ebpextensions\upgrade_ext" List.ItemID="536671903" List.ParentItemID="536671903">
				<list name="standard_upgrades" overrideParent="True">
					<instance_reference name="upgrade" value="upgrade\races\rus\research\upgrade_wooden_castle_arrowslits_rus" overrideParent="True" List.ItemID="-755436356" />
				</list>
			</template_reference>
			<template_reference name="exts" value="ebpextensions\site_ext" List.ItemID="389041388" List.ParentItemID="389041388">
				<bool name="snap_to_construction_grid" value="True" overrideParent="True" />
			</template_reference>
			<template_reference name="exts" value="ebpextensions\construction_ext" List.ItemID="1700796307" List.ParentItemID="1700796307">
				<template_reference name="construction_health_option" value="options\ebpextensions\constructionext\construction_health_option">
					<float name="initial_health" value="200" overrideParent="True" />
				</template_reference>
				<group name="on_construction_complete_state_tree_refs">
					<string name="while_construction_complete_entity_state_tree_ref" value="building_construction_complete\buildings\outpost_construction_complete" overrideParent="True" />
				</group>
				<bool name="construction_site_erase_inactive" value="False" overrideParent="True" />
			</template_reference>
			<template_reference name="exts" value="ebpextensions\spawner_ext" List.ItemID="32036034" List.ParentItemID="32036034">
				<instance_reference name="rally_pass_type" value="pass_types\infantry" overrideParent="True" />
				<list name="spawn_items" overrideParent="True">
					<group name="spawn_item" comment="spearman - castle age" List.ItemID="1758454390">
						<instance_reference name="entity" value="" />
						<instance_reference name="squad" value="sbps\races\rus\unit_horsearcher_3_rus" overrideParent="True" />
						<bool name="spawn_at_map_entry_point" value="False" />
						<group name="ui_position">
							<int name="ui_position_row" value="1" />
							<int name="ui_position_column" value="1" overrideParent="True" />
						</group>
						<instance_reference name="ui_menu" value="" />
						<int name="number_to_spawn" value="1" />
						<enum_table name="item_cost_adjustment">
							<float name="action" value="0" />
							<float name="command" value="0" />
							<float name="popcap" value="0" />
							<float name="food" value="0" />
							<float name="wood" value="0" />
							<float name="stone" value="0" />
							<float name="gold" value="0" />
							<float name="militia_hre" value="0" />
							<float name="merc_byz" value="0" />
						</enum_table>
						<locstring name="ui_screen_name" value="0" />
						<locstring name="ui_help_text" value="0" />
						<bool name="can_be_cancelled" value="True" />
						<int name="number_to_queue_up_to_when_modified" value="5" />
						<list name="additional_squads">
						</list>
						<instance_reference name="hotkey_binding" value="hotkeys\hotkey_binding\building_archery_range\produce_horsearcher" overrideParent="True" />
						<template_reference name="ui_info_extended" value="tables\ui_info_ext">
							<template_reference name="command_card_info" value="">
							</template_reference>
							<template_reference name="quick_abilities_info" value="">
							</template_reference>
							<template_reference name="quick_commands_info" value="ui_quick_commands_info">
								<int name="quick_commands_slot_index" value="0" />
								<enum name="quick_commands_hotkey" value="x_quick_command_y" />
								<int name="quick_commands_priority" value="5" />
							</template_reference>
							<template_reference name="quick_formation_info" value="">
							</template_reference>
							<template_reference name="ping_menu_info" value="">
							</template_reference>
							<enum name="category" value="Economic" />
							<template_reference name="quick_commands_launch_hud_info" value="ui_quick_commands_launch_hud_info">
								<enum name="quick_commands_hotkey" value="x_quick_command_y" />
								<int name="quick_commands_priority" value="5" />
								<int name="quick_commands_slot_index" value="2" />
								<enum name="quick_commands_hold_time" value="quick_command_hold_time" />
							</template_reference>
							<template_reference name="relic_radial_menu_info" value="relic_radial_menu\relic_radial_menu_info">
								<instance_reference name="menu" value="relic_radial_menu\relic_radial_menu\default" />
								<int name="nominal_index" value="0" />
								<int name="priority" value="0" />
								<instance_reference name="linked" value="upgrade\races\common\units\upgrade_unit_spearman_4" />
							</template_reference>
							<enum name="observer_type" value="Disabled" />
							<group name="issuable_info">
								<bool name="is_secondary" value="False" />
								<instance_reference name="secondary_issuable" value="" />
							</group>
						</template_reference>
						<file name="ui_icon_name" value="" />
						<string name="ui_tooltip_data_template" value="" />
					</group>
				</list>
				<int name="max_queue_size_override" value="30" overrideParent="True" />
			</template_reference>
			<template_reference name="exts" value="ebpextensions\combat_ext" List.ItemID="2086910227" List.ParentItemID="2086910227">
				<list name="hardpoints" overrideParent="True">
					<group name="hardpoint" comment="Arrowslits Slot" List.ItemID="1472238325">
						<float name="parent_hardpoint" value="-1" />
						<list name="weapon_table">
							<group name="weapon" List.ItemID="-966991841">
								<group name="heading">
									<float name="x" value="0" />
									<float name="y" value="0.3" />
									<float name="z" value="1" />
								</group>
								<float name="length" value="0" />
								<group name="origin">
									<float name="x" value="0" />
									<float name="y" value="6" />
									<float name="z" value="0" />
								</group>
								<enum name="type" value="default" />
								<template_reference name="weapon_entity_attachment" value="options\attachment_types\entity_create_attachment">
									<template_reference name="entity_attach_data" value="attachments\attach_data_entity">
										<template_reference name="attach_data" value="attachments\attach_data">
											<string name="marker_name_parent" value="" />
											<string name="parent_rigidbody_target_name" value="" />
											<enum name="game_object_attachment_type" value="scenegraph" />
										</template_reference>
										<instance_reference name="ebp" value="ebps\races\core\weapons\wpn_range_keep_arrows_a" overrideParent="True" />
										<group name="attachment_flags">
											<bool name="sim_only" value="False" />
											<bool name="no_pathfinding" value="False" />
											<bool name="not_snappable" value="False" />
											<bool name="restore_snap_to_ground_on_detach" value="False" />
											<bool name="no_sim_update" value="True" />
											<bool name="join_parent_squad" value="False" />
											<bool name="redirect_damage_to_parent_entity" value="True" />
											<bool name="assign_as_attachment_combat_leader" value="False" />
											<bool name="assign_as_attachment_movement_leader" value="False" />
											<bool name="receive_parent_animations" value="False" />
											<bool name="receive_parent_death" value="False" />
										</group>
									</template_reference>
									<list name="possible_blueprint_updates">
									</list>
								</template_reference>
								<template_reference name="non_entity_weapon_wrapper" value="">
								</template_reference>
							</group>
						</list>
						<bool name="receives_attack_commands" value="True" />
						<string name="base_marker" value="" />
						<list name="preferred_inventory_item_categories">
						</list>
						<list name="firing_offset_markers">
							<string name="marker" value="fx_muz_arrow_00" List.ItemID="961581687" />
							<string name="marker" value="fx_muz_arrow_01" List.ItemID="-2025153447" />
							<string name="marker" value="fx_muz_arrow_02" List.ItemID="-963541873" />
							<string name="marker" value="fx_muz_arrow_03" List.ItemID="148566359" />
						</list>
						<bool name="initialize_weapons_on_creation" value="True" overrideParent="True" />
						<string name="offhand_marker" value="" />
					</group>
					<group name="hardpoint" comment="Arrowslits Slot" List.ItemID="-1728556735">
						<float name="parent_hardpoint" value="-1" />
						<list name="weapon_table">
							<group name="weapon" List.ItemID="173896382">
								<group name="heading">
									<float name="x" value="0" />
									<float name="y" value="0.3" />
									<float name="z" value="1" />
								</group>
								<float name="length" value="0" />
								<group name="origin">
									<float name="x" value="0" />
									<float name="y" value="6" />
									<float name="z" value="0" />
								</group>
								<enum name="type" value="default" />
								<template_reference name="weapon_entity_attachment" value="options\attachment_types\entity_create_attachment">
									<template_reference name="entity_attach_data" value="attachments\attach_data_entity">
										<template_reference name="attach_data" value="attachments\attach_data">
											<string name="marker_name_parent" value="" />
											<string name="parent_rigidbody_target_name" value="" />
											<enum name="game_object_attachment_type" value="scenegraph" />
										</template_reference>
										<instance_reference name="ebp" value="ebps\races\core\weapons\wpn_range_keep_arrows_b" overrideParent="True" />
										<group name="attachment_flags">
											<bool name="sim_only" value="False" />
											<bool name="no_pathfinding" value="False" />
											<bool name="not_snappable" value="False" />
											<bool name="restore_snap_to_ground_on_detach" value="False" />
											<bool name="no_sim_update" value="True" />
											<bool name="join_parent_squad" value="False" />
											<bool name="redirect_damage_to_parent_entity" value="True" />
											<bool name="assign_as_attachment_combat_leader" value="False" />
											<bool name="assign_as_attachment_movement_leader" value="False" />
											<bool name="receive_parent_animations" value="False" />
											<bool name="receive_parent_death" value="False" />
										</group>
									</template_reference>
									<list name="possible_blueprint_updates">
									</list>
								</template_reference>
								<template_reference name="non_entity_weapon_wrapper" value="">
								</template_reference>
							</group>
						</list>
						<bool name="receives_attack_commands" value="True" />
						<string name="base_marker" value="" />
						<list name="preferred_inventory_item_categories">
						</list>
						<list name="firing_offset_markers">
							<string name="marker" value="fx_muz_arrow_00" List.ItemID="1961444485" />
							<string name="marker" value="fx_muz_arrow_01" List.ItemID="1942919196" />
							<string name="marker" value="fx_muz_arrow_02" List.ItemID="-945032142" />
							<string name="marker" value="fx_muz_arrow_03" List.ItemID="-48605376" />
						</list>
						<bool name="initialize_weapons_on_creation" value="True" overrideParent="True" />
						<string name="offhand_marker" value="" />
					</group>
				</list>
			</template_reference>
			<template_reference name="exts" value="ebpextensions\action_apply_ext" List.ItemID="1012768552" List.ParentItemID="1012768552">
				<list name="action_state_trees">
					<group name="container" List.ItemID="-1982514905" List.ListAction="Append">
						<string name="state_tree" value="building_regenerate_hre_brawl" />
					</group>
				</list>
			</template_reference>
			<template_reference name="exts" value="ebpextensions\ability_ext" List.ItemID="-589861990" List.ParentItemID="-589861990">
				<list name="abilities" overrideParent="True">
				</list>
			</template_reference>
		</list>
		<uniqueid name="pbgid" value="133438" />
		<instance_reference name="parent_pbg" value="ebps\races\core\buildings\building_defense_outpost" />
	</variant>
</instance>